Metadata-Version: 2.1
Name: find-my-favorite-cat
Version: 0.1
Summary: Find cat information that matches the input from user.
Home-page: https://github.com/hong-chen/find-my-favorite-cat
Author: Hong Chen, Yixing Shao
Author-email: me@hongchen.cz, yixingshao@foxmail.com
License: MIT
Keywords: find cat
Platform: UNKNOWN
Classifier: Development Status :: 2 - Pre-Alpha
Classifier: License :: OSI Approved :: MIT License
Classifier: Programming Language :: Python :: 3.6
Classifier: Topic :: Internet :: WWW/HTTP :: Dynamic Content
Requires-Python: ~=3.6
